make.py
setup.py
docs/html/genindex.html
docs/html/index.html
docs/html/modindex.html
docs/html/search.html
docs/html/searchindex.json
docs/html/.doctrees/environment.pickle
docs/html/.doctrees/index.doctree
docs/html/.doctrees/modules/logger.doctree
docs/html/_sources/index.txt
docs/html/_sources/modules/logger.txt
docs/html/_static/contents.png
docs/html/_static/default.css
docs/html/_static/doctools.js
docs/html/_static/file.png
docs/html/_static/interface.js
docs/html/_static/jquery.js
docs/html/_static/minus.png
docs/html/_static/navigation.png
docs/html/_static/plus.png
docs/html/_static/pygments.css
docs/html/_static/rightsidebar.css
docs/html/_static/searchtools.js
docs/html/_static/sphinxdoc.css
docs/html/_static/stickysidebar.css
docs/html/_static/traditional.css
docs/html/modules/logger.html
docs/source/conf.py
docs/source/index.rst
src/pyjld/__init__.py
src/pyjld.logger.egg-info/PKG-INFO
src/pyjld.logger.egg-info/SOURCES.txt
src/pyjld.logger.egg-info/dependency_links.txt
src/pyjld.logger.egg-info/namespace_packages.txt
src/pyjld.logger.egg-info/top_level.txt
src/pyjld.logger.egg-info/zip-safe
src/pyjld/logger/__init__.py
src/pyjld/logger/logger.py
tests/tests.py
tests/tests.txt