Metadata-Version: 1.0
Name: pyjld.logger
Version: 0.6
Summary: pyjld.logger: cross-platform logging utilities
Home-page: http://pyjld.googlecode.com/svn/trunk/pyjld.logger/tags/0.6/docs/index.html
Author: Jean-Lou Dupont
Author-email: python (at) jldupont.com
License: UNKNOWN
Platform: UNKNOWN
Classifier: Development Status :: 4 - Beta
Classifier: Intended Audience :: Developers
Classifier: License :: Public Domain
Classifier: Programming Language :: Python
Classifier: Topic :: Software Development :: Libraries :: Python Modules
Classifier: Operating System :: Microsoft :: Windows
Classifier: Operating System :: POSIX
